GcpShangDeRengongzhinengShiyongZhinanChuyiFix1/README.md
GcpShangDeRengongzhinengShiyongZhinanChuyiFix1/__init__.py
GcpShangDeRengongzhinengShiyongZhinanChuyiFix1/__main__.py
GcpShangDeRengongzhinengShiyongZhinanChuyiFix1/file.epub
GcpShangDeRengongzhinengShiyongZhinanChuyiFix1/index.html
GcpShangDeRengongzhinengShiyongZhinanChuyiFix1/css/__init__.py
GcpShangDeRengongzhinengShiyongZhinanChuyiFix1/css/annotations.css
GcpShangDeRengongzhinengShiyongZhinanChuyiFix1/css/main.css
GcpShangDeRengongzhinengShiyongZhinanChuyiFix1/css/normalize.css
GcpShangDeRengongzhinengShiyongZhinanChuyiFix1/css/popup.css
GcpShangDeRengongzhinengShiyongZhinanChuyiFix1/font/__init__.py
GcpShangDeRengongzhinengShiyongZhinanChuyiFix1/font/fontello.eot
GcpShangDeRengongzhinengShiyongZhinanChuyiFix1/font/fontello.svg
GcpShangDeRengongzhinengShiyongZhinanChuyiFix1/font/fontello.ttf
GcpShangDeRengongzhinengShiyongZhinanChuyiFix1/font/fontello.woff
GcpShangDeRengongzhinengShiyongZhinanChuyiFix1/img/__init__.py
GcpShangDeRengongzhinengShiyongZhinanChuyiFix1/img/annotator-glyph-sprite.png
GcpShangDeRengongzhinengShiyongZhinanChuyiFix1/img/annotator-icon-sprite.png
GcpShangDeRengongzhinengShiyongZhinanChuyiFix1/img/apple-touch-icon.png
GcpShangDeRengongzhinengShiyongZhinanChuyiFix1/img/cancelfullscreen.png
GcpShangDeRengongzhinengShiyongZhinanChuyiFix1/img/close.png
GcpShangDeRengongzhinengShiyongZhinanChuyiFix1/img/fullscreen.png
GcpShangDeRengongzhinengShiyongZhinanChuyiFix1/img/loader.gif
GcpShangDeRengongzhinengShiyongZhinanChuyiFix1/img/menu-icon.png
GcpShangDeRengongzhinengShiyongZhinanChuyiFix1/img/save.png
GcpShangDeRengongzhinengShiyongZhinanChuyiFix1/img/saved.png
GcpShangDeRengongzhinengShiyongZhinanChuyiFix1/img/settings-s.png
GcpShangDeRengongzhinengShiyongZhinanChuyiFix1/img/settings.png
GcpShangDeRengongzhinengShiyongZhinanChuyiFix1/img/star.png
GcpShangDeRengongzhinengShiyongZhinanChuyiFix1/js/__init__.py
GcpShangDeRengongzhinengShiyongZhinanChuyiFix1/js/epub.js
gcp_shang_de_rengongzhineng_shiyong_zhinan_chuyi_fix1-2025.3.25.1.dist-info/METADATA
gcp_shang_de_rengongzhineng_shiyong_zhinan_chuyi_fix1-2025.3.25.1.dist-info/WHEEL
gcp_shang_de_rengongzhineng_shiyong_zhinan_chuyi_fix1-2025.3.25.1.dist-info/entry_points.txt
gcp_shang_de_rengongzhineng_shiyong_zhinan_chuyi_fix1-2025.3.25.1.dist-info/top_level.txt
gcp_shang_de_rengongzhineng_shiyong_zhinan_chuyi_fix1-2025.3.25.1.dist-info/RECORD
